[
  {
    "codigo": "GM2025-701",
    "nombre": "Melina Lopez Suasnabar",
       "curso": "Tuberculosis En la Práctica Clínica",
    "fecha": "25/07/2025",
    "link": "https://drive.google.com/file/d/1RvPk7h6V6NNHCL9yRjUTSJl_pKAa3mmZ/view?usp=sharing"
  },
  {
    "codigo": "GM2025-702",
    "nombre": "Juan Pablo Leon Iriarte",
      "curso": "Tuberculosis En la Práctica Clínica",
    "fecha": "25/07/2025",
    "link": "https://drive.google.com/file/d/1RvPk7h6V6NNHCL9yRjUTSJl_pKAa3mmZ/view?usp=sharing"
  },
    {
    "codigo": "GM2025-703",
    "nombre": "Ciro Gonzalo Zavala Gama",
      "curso": "Tuberculosis En la Práctica Clínica",
    "fecha": "25/07/2025",
    "link": "https://drive.google.com/file/d/1RvPk7h6V6NNHCL9yRjUTSJl_pKAa3mmZ/view?usp=sharing"
  },
    {
    "codigo": "GM2025-704",
    "nombre": "Victor Loayza Tasayco",
     "curso": "Tuberculosis En la Práctica Clínica",
    "fecha": "25/07/2025",
    "link": "https://drive.google.com/file/d/1RvPk7h6V6NNHCL9yRjUTSJl_pKAa3mmZ/view?usp=sharing"
  },
    {
    "codigo": "GM2025-705",
    "nombre": "Diego Bilvao Huaynoca Mamani",
   "curso": "Tuberculosis En la Práctica Clínica",
    "fecha": "25/07/2025",
    "link": "https://drive.google.com/file/d/1RvPk7h6V6NNHCL9yRjUTSJl_pKAa3mmZ/view?usp=sharing"
  },
    {
    "codigo": "GM2025-706",
    "nombre": "Yubica Allison Leon Ramos",
      "curso": "Tuberculosis En la Práctica Clínica",
    "fecha": "25/07/2025",
    "link": "https://drive.google.com/file/d/1RvPk7h6V6NNHCL9yRjUTSJl_pKAa3mmZ/view?usp=sharing"
  },
    {
    "codigo": "GM2025-707",
    "nombre": "Carlos Geraldo Fernández Narváez",
    "curso": "Tuberculosis En la Práctica Clínica",
    "fecha": "25/07/2025",
    "link": "https://drive.google.com/file/d/1RvPk7h6V6NNHCL9yRjUTSJl_pKAa3mmZ/view?usp=sharing"
  },
    {
    "codigo": "GM2025-708",
    "nombre": "Karem Melissa Aldazábal Barbarán",
     "curso": "Tuberculosis En la Práctica Clínica",
    "fecha": "25/07/2025",
    "link": "https://drive.google.com/file/d/1RvPk7h6V6NNHCL9yRjUTSJl_pKAa3mmZ/view?usp=sharing"
  },
    {
    "codigo": "GM2025-709",
    "nombre": "Phiero Armando Martínez Alcantara",
     "curso": "Tuberculosis En la Práctica Clínica",
    "fecha": "25/07/2025",
    "link": "https://drive.google.com/file/d/1RvPk7h6V6NNHCL9yRjUTSJl_pKAa3mmZ/view?usp=sharing"
  },
    {
    "codigo": "GM2025-710",
    "nombre": "José Carlos Villavicencio Benites",
   "curso": "Tuberculosis En la Práctica Clínica",
    "fecha": "25/07/2025",
    "link": "https://drive.google.com/file/d/1RvPk7h6V6NNHCL9yRjUTSJl_pKAa3mmZ/view?usp=sharing"
  },
    {
    "codigo": "GM2025-711",
    "nombre": "Jesus Alonso Yaya Delgado",
      "curso": "Tuberculosis En la Práctica Clínica",
    "fecha": "25/07/2025",
    "link": "https://drive.google.com/file/d/1RvPk7h6V6NNHCL9yRjUTSJl_pKAa3mmZ/view?usp=sharing"
  },
    {
    "codigo": "GM2025-712",
    "nombre": "Nataly Susana Vasquez Hinostroza",
       "curso": "Tuberculosis En la Práctica Clínica",
    "fecha": "25/07/2025",
    "link": "https://drive.google.com/file/d/1RvPk7h6V6NNHCL9yRjUTSJl_pKAa3mmZ/view?usp=sharing"
  },
    {
    "codigo": "GM2025-713",
    "nombre": "Gladys Margarita Nolasco Santiago",
   "curso": "Tuberculosis En la Práctica Clínica",
    "fecha": "25/07/2025",
    "link": "https://drive.google.com/file/d/1RvPk7h6V6NNHCL9yRjUTSJl_pKAa3mmZ/view?usp=sharing"
  },
    {
    "codigo": "GM2025-714",
    "nombre": "Janeth Susy Cuyubamba Garcia",
     "curso": "Tuberculosis En la Práctica Clínica",
    "fecha": "25/07/2025",
    "link": "https://drive.google.com/file/d/1RvPk7h6V6NNHCL9yRjUTSJl_pKAa3mmZ/view?usp=sharing"
  },
    {
    "codigo": "GM2025-715",
    "nombre": "Roberto Gabriel Flores Tejada",
       "curso": "Tuberculosis En la Práctica Clínica",
    "fecha": "25/07/2025",
    "link": "https://drive.google.com/file/d/1RvPk7h6V6NNHCL9yRjUTSJl_pKAa3mmZ/view?usp=sharing"
  },
    {
    "codigo": "GM2025-716",
    "nombre": "Claudia More Verde",
       "curso": "Tuberculosis En la Práctica Clínica",
    "fecha": "25/07/2025",
    "link": "https://drive.google.com/file/d/1RvPk7h6V6NNHCL9yRjUTSJl_pKAa3mmZ/view?usp=sharing"
  },
    {
    "codigo": "GM2025-717",
    "nombre": "Fernando Renzo Garayar Burneo",
    "curso": "Tuberculosis En la Práctica Clínica",
    "fecha": "25/07/2025",
    "link": "https://drive.google.com/file/d/1RvPk7h6V6NNHCL9yRjUTSJl_pKAa3mmZ/view?usp=sharing"
  },
    {
    "codigo": "GM2025-718",
    "nombre": "Cinthia Elvira Zambrano Gomez",
      "curso": "Tuberculosis En la Práctica Clínica",
    "fecha": "25/07/2025",
    "link": "https://drive.google.com/file/d/1RvPk7h6V6NNHCL9yRjUTSJl_pKAa3mmZ/view?usp=sharing"
  },
    {
    "codigo": "GM2025-719",
    "nombre": "Vivian Bogado Chavez",
     "curso": "Tuberculosis En la Práctica Clínica",
    "fecha": "25/07/2025",
    "link": "https://drive.google.com/file/d/1RvPk7h6V6NNHCL9yRjUTSJl_pKAa3mmZ/view?usp=sharing"
  },
    {
    "codigo": "GM2025-720",
    "nombre": "Evelyng Mirella Serveleón Nieto",
       "curso": "Tuberculosis En la Práctica Clínica",
    "fecha": "25/07/2025",
    "link": "https://drive.google.com/file/d/1RvPk7h6V6NNHCL9yRjUTSJl_pKAa3mmZ/view?usp=sharing"
  },
    {
    "codigo": "GM2025-721",
    "nombre": "Godofredo Caro Agüero",
      "curso": "Tuberculosis En la Práctica Clínica",
    "fecha": "25/07/2025",
    "link": "https://drive.google.com/file/d/1RvPk7h6V6NNHCL9yRjUTSJl_pKAa3mmZ/view?usp=sharing"
  },
    {
    "codigo": "GM2025-722",
    "nombre": "Jessica Rubi Reynel Chávez",
    "curso": "Tuberculosis En la Práctica Clínica",
    "fecha": "25/07/2025",
    "link": "https://drive.google.com/file/d/1RvPk7h6V6NNHCL9yRjUTSJl_pKAa3mmZ/view?usp=sharing"
  },
    {
    "codigo": "GM2025-723",
    "nombre": "Roxana Rita Cavani Rojas",
       "curso": "Tuberculosis En la Práctica Clínica",
    "fecha": "25/07/2025",
    "link": "https://drive.google.com/file/d/1RvPk7h6V6NNHCL9yRjUTSJl_pKAa3mmZ/view?usp=sharing"
  },
    {
    "codigo": "GM2025-724",
    "nombre": "Anny Estéfany Vidal Viera",
    "curso": "Soporte Vital Básico",
    "fecha": "03/08/2025",
    "link": "https://drive.google.com/uc?id=1A2B3C4DEFGHIJKLMNO"
  },
    {
    "codigo": "GM2025-725",
    "nombre": "Zocimo Richard Condori Cari",
       "curso": "Tuberculosis En la Práctica Clínica",
    "fecha": "25/07/2025",
    "link": "https://drive.google.com/file/d/1RvPk7h6V6NNHCL9yRjUTSJl_pKAa3mmZ/view?usp=sharing"
  },
    {
    "codigo": "GM2025-726",
    "nombre": "Gloria Milagros Medina Santiago",
       "curso": "Tuberculosis En la Práctica Clínica",
    "fecha": "25/07/2025",
    "link": "https://drive.google.com/file/d/1RvPk7h6V6NNHCL9yRjUTSJl_pKAa3mmZ/view?usp=sharing"
  },
    {
    "codigo": "GM2025-727",
    "nombre": "Ariel Carlos Cornejo Ortiz",
       "curso": "Tuberculosis En la Práctica Clínica",
    "fecha": "25/07/2025",
    "link": "https://drive.google.com/file/d/1RvPk7h6V6NNHCL9yRjUTSJl_pKAa3mmZ/view?usp=sharing"
  },
    {
    "codigo": "GM2025-728",
    "nombre": "Joseph Andres Mendoza Calle",
     "curso": "Tuberculosis En la Práctica Clínica",
    "fecha": "25/07/2025",
    "link": "https://drive.google.com/file/d/1RvPk7h6V6NNHCL9yRjUTSJl_pKAa3mmZ/view?usp=sharing"
  },
    {
    "codigo": "GM2025-729",
    "nombre": "Gonzalo Caro Alvarado",
       "curso": "Tuberculosis En la Práctica Clínica",
    "fecha": "25/07/2025",
    "link": "https://drive.google.com/file/d/1RvPk7h6V6NNHCL9yRjUTSJl_pKAa3mmZ/view?usp=sharing"
  },
    {
    "codigo": "GM2025-730",
    "nombre": "Sergio Huber Lujan Garcia",
      "curso": "Tuberculosis En la Práctica Clínica",
    "fecha": "25/07/2025",
    "link": "https://drive.google.com/file/d/1RvPk7h6V6NNHCL9yRjUTSJl_pKAa3mmZ/view?usp=sharing"
  },
    {
    "codigo": "GM2025-731",
    "nombre": "Alex Hinostroza Huamán",
      "curso": "Tuberculosis En la Práctica Clínica",
    "fecha": "25/07/2025",
    "link": "https://drive.google.com/file/d/1RvPk7h6V6NNHCL9yRjUTSJl_pKAa3mmZ/view?usp=sharing"
  },
    {
    "codigo": "GM2025-732",
    "nombre": "Enrique Alfonso De La Cruz Chuquilin",
     "curso": "Tuberculosis En la Práctica Clínica",
    "fecha": "25/07/2025",
    "link": "https://drive.google.com/file/d/1RvPk7h6V6NNHCL9yRjUTSJl_pKAa3mmZ/view?usp=sharing"
  },
    {
    "codigo": "GM2025-733",
    "nombre": "Gilda Maria Bueno Bueno",
   "curso": "Tuberculosis En la Práctica Clínica",
    "fecha": "25/07/2025",
    "link": "https://drive.google.com/file/d/1RvPk7h6V6NNHCL9yRjUTSJl_pKAa3mmZ/view?usp=sharing"
  },
    {
    "codigo": "GM2025-734",
    "nombre": "Diana Valenzuela López",
   "curso": "Tuberculosis En la Práctica Clínica",
    "fecha": "25/07/2025",
    "link": "https://drive.google.com/file/d/1RvPk7h6V6NNHCL9yRjUTSJl_pKAa3mmZ/view?usp=sharing"
  },
    {
    "codigo": "GM2025-735",
    "nombre": "Lucia Victoria Retuerto Riquelme",
   "curso": "Tuberculosis En la Práctica Clínica",
    "fecha": "25/07/2025",
    "link": "https://drive.google.com/file/d/1RvPk7h6V6NNHCL9yRjUTSJl_pKAa3mmZ/view?usp=sharing"
  },
    {
    "codigo": "GM2025-736",
    "nombre": "José Marcelino Vázquez Millán",
     "curso": "Tuberculosis En la Práctica Clínica",
    "fecha": "25/07/2025",
    "link": "https://drive.google.com/file/d/1RvPk7h6V6NNHCL9yRjUTSJl_pKAa3mmZ/view?usp=sharing"
  },
    {
    "codigo": "GM2025-737",
    "nombre": "Henry Dennis Huamanlazo Ramírez",
    "curso": "Tuberculosis En la Práctica Clínica",
    "fecha": "25/07/2025",
    "link": "https://drive.google.com/file/d/1RvPk7h6V6NNHCL9yRjUTSJl_pKAa3mmZ/view?usp=sharing"
  },
    {
    "codigo": "GM2025-738",
    "nombre": "Amalyn Claudio Cruz",
   "curso": "Tuberculosis En la Práctica Clínica",
    "fecha": "25/07/2025",
    "link": "https://drive.google.com/file/d/1RvPk7h6V6NNHCL9yRjUTSJl_pKAa3mmZ/view?usp=sharing"
  },
    {
    "codigo": "GM2025-739",
    "nombre": "Idaura Huaman Calle",
     "curso": "Tuberculosis En la Práctica Clínica",
    "fecha": "25/07/2025",
    "link": "https://drive.google.com/file/d/1RvPk7h6V6NNHCL9yRjUTSJl_pKAa3mmZ/view?usp=sharing"
  }
]




